circuit.v
module test_circuit (
    input A,
    input B,
    input C,
    output D,
    output E );

    wire w1;

    assign w1 = A & B;
    assign E = ~C;
    assign D = w1 | E;

    

endmodule

circuit_tb.v
`timescale 1ns/1ns
// import circuit code
`include "circuit.v"

module sample_tb;

// declare inputs as registers
reg A;
reg B;
reg C;

// declare outputs as wires
wire D;
wire E;

// initialize circuit module
test_circuit uut(A, B, C, D, E);

// this block will only run in simulation and cannot be mapped to hardware
initial begin
    // create dump file
    $dumpfile("circuit_tb.vcd");
    $dumpvars(0, sample_tb);

    // start writing values
    {A, B, C} = 3'b000;
    #10; 

    {A, B, C} = 3'b001;
    #10;

    {A, B, C} = 3'b010;
    #10;

    {A, B, C} = 3'b011;
    #10;

    {A, B, C} = 3'b100;
    #10;

    {A, B, C} = 3'b101;
    #10;

    {A, B, C} = 3'b110;
    #10;

    {A, B, C} = 3'b111;
    #10;

    $display("Test complete! Hell yeah MF");
end

endmodule

circuit_tb.vcd
$date
	Thu Aug 29 13:46:04 2024
$end
$version
	Icarus Verilog
$end
$timescale
	1ns
$end
$scope module sample_tb $end
$var wire 1 ! E $end
$var wire 1 " D $end
$var reg 1 # A $end
$var reg 1 $ B $end
$var reg 1 % C $end
$scope module uut $end
$var wire 1 # A $end
$var wire 1 $ B $end
$var wire 1 % C $end
$var wire 1 " D $end
$var wire 1 ! E $end
$var wire 1 & w1 $end
$upscope $end
$upscope $end
$enddefinitions $end
$comment Show the parameter values. $end
$dumpall
$end
#0
$dumpvars
0&
0%
0$
0#
1"
1!
$end
#10
0"
0!
1%
#20
1"
1!
1$
0%
#30
0"
0!
1%
#40
1"
1!
1#
0$
0%
#50
0"
0!
1%
#60
1"
1&
1!
1$
0%
#70
0!
1%
